pecblocks/__init__.py
pecblocks/api.py
pecblocks/common.py
pecblocks/pv3_functions.py
pecblocks/pv3_poly.py
pecblocks/util.py
pecblocks/version.py
pecblocks-0.0.4.dist-info/LICENSE.txt
pecblocks-0.0.4.dist-info/METADATA
pecblocks-0.0.4.dist-info/WHEEL
pecblocks-0.0.4.dist-info/top_level.txt
pecblocks-0.0.4.dist-info/RECORD
