Metadata-Version: 2.1
Name: pecblocks
Version: 0.0.4
Summary: pecblocks: Generalized block diagram modeling of power electronic converters for grid solar and storage applications.
Home-page: https://github.com/pnnl/pecblocks
Author: Tom McDermott, Qiuhua Huang, and Yuan Liu
Author-email: T.McDermott@IEEE.org
License: BSD
Project-URL: Bug Tracker, https://github.com/pnnl/pecblocks/issues
Classifier: License :: OSI Approved :: BSD License
Classifier: Operating System :: OS Independent
Classifier: Programming Language :: Python :: 3.7
Classifier: Development Status :: 4 - Beta
Classifier: Environment :: Console
Classifier: Intended Audience :: Developers
Classifier: Intended Audience :: Education
Classifier: Intended Audience :: Science/Research
Classifier: Topic :: Scientific/Engineering
License-File: LICENSE.txt
Requires-Dist: dynonet >=0.1.2
Requires-Dist: harold >=1.0.1
Requires-Dist: control >=0.9.2
Requires-Dist: h5py >=3.7.0
